[{"track_id": "6xGruZOHLs39ZbVccQTuPZ", "track_name": "Glimpse of Us", "artist_name": "Joji", "album_name": "Glimpse of Us"}, {"track_id": "7m9OqQk4RVRkw9JJdeAw96", "track_name": "Jocelyn Flores", "artist_name": "XXXTENTACION", "album_name": "17"}, {"track_id": "7qEHsqek33rTcFNT9PFqLf", "track_name": "Someone You Loved", "artist_name": "Lewis Capaldi", "album_name": "Divinely Uninspired To A Hellish Extent"}, {"track_id": "6Ky8ROf2VWY5vwoGfMet7x", "track_name": "Forever & Again (From Barbie The Album)", "artist_name": "The Kid LAROI", "album_name": "Forever & Again (From Barbie The Album)"}, {"track_id": "7nfDp2MzfvzcWYKir7zH2N", "track_name": "It's All Too Much", "artist_name": "Nick Bonin", "album_name": "It's All Too Much"}, {"track_id": "3NG9DUSmm78ay565a6QQdp", "track_name": "Somebody", "artist_name": "Yung Pooda", "album_name": "Somebody"}, {"track_id": "5eHq2vcmHfFZ3rIKwxh6Ly", "track_name": "Little Girl (feat. raynn)", "artist_name": "MBNel", "album_name": "The Lift Off"}, {"track_id": "4H9lAeM86hkuiQzEhvM15L", "track_name": "Deja Vu", "artist_name": "Rocco", "album_name": "Wxlf Pack"}, {"track_id": "4StcEPgput760vaneW8l4J", "track_name": "Good Intentions", "artist_name": "MBNel", "album_name": "The Lift Off"}, {"track_id": "7LuKxq6yJJ3EhMTcavy4S3", "track_name": "SOCKS 4 THE LOW", "artist_name": "Swxm", "album_name": "SOCKS 4 THE LOW"}, {"track_id": "1odExI7RdWc4BT515LTAwj", "track_name": "Daylight", "artist_name": "David Kushner", "album_name": "Daylight"}, {"track_id": "0rc9XLNs7KZXu2ASA3LbL8", "track_name": "MISTAKE", "artist_name": "NF", "album_name": "HOPE"}, {"track_id": "0mGFn11FzuIiMJbdqOEaKW", "track_name": "U & I - Unplugged", "artist_name": "Zzz.", "album_name": "U & I"}, {"track_id": "2Egw4s2Lc6h6T3tD8h0qXq", "track_name": "Solo", "artist_name": "Geo", "album_name": "Solo"}, {"track_id": "1fTNu0OPdWr8XS05SjDvER", "track_name": "Bad Guy", "artist_name": "Amarii", "album_name": "Bad Guy"}, {"track_id": "74wMB8lOMpM6GFAlAK3P6j", "track_name": "Again & Again", "artist_name": "Big Boss Mulaa", "album_name": "Again & Again"}, {"track_id": "1l0wPhFZP1kWkZNQrrYrGy", "track_name": "RUNNING", "artist_name": "NF", "album_name": "HOPE"}, {"track_id": "5oGBWVYJfKCQhX7EymW5FM", "track_name": "Select A Button", "artist_name": "Oshua", "album_name": "Select A Button"}, {"track_id": "3ZUzlQ6sR1O6k8GhJMa4Cs", "track_name": "Pharmacy", "artist_name": "Wett Brain", "album_name": "Pharmacy"}, {"track_id": "6j5BK1cFX9TjJd5EXHGgAn", "track_name": "The Light", "artist_name": "Juice WRLD", "album_name": "The Light"}, {"track_id": "1lKP2fdK4pZvXc0FXU9o2Y", "track_name": "Was This Love?", "artist_name": "mxsta ree", "album_name": "Was This Love?"}, {"track_id": "1yvArCvZLTHiawRdWKSAWj", "track_name": "I\u2019m a Mess (with YUNGBLUD)", "artist_name": "Avril Lavigne", "album_name": "I\u2019m a Mess (with YUNGBLUD)"}, {"track_id": "7bSxVrKfyHDkjWjgObbl6z", "track_name": "Burn It Down", "artist_name": "Kjersti Long", "album_name": "Burn It Down"}, {"track_id": "2c6RChryDMC735TAdl2Nyo", "track_name": "The Weekend", "artist_name": "Sycklone", "album_name": "The Weekend"}, {"track_id": "7dinBECf2hNhnawGdAGT2B", "track_name": "Sad & Alone", "artist_name": "Zzz.", "album_name": "Sad & Alone"}, {"track_id": "2RJAKIw6nIkgZVsAIKhmqz", "track_name": "In My Head", "artist_name": "Juice WRLD", "album_name": "In My Head"}, {"track_id": "6L4XGeAdRRC32vVJpp8MdM", "track_name": "Face 2 Face", "artist_name": "Juice WRLD", "album_name": "Face 2 Face"}, {"track_id": "2LCGFBu1ej6zt4r1VGPjny", "track_name": "GONE", "artist_name": "NF", "album_name": "HOPE"}, {"track_id": "5c897G7mIXudNKytpLLeeX", "track_name": "sunset eyes", "artist_name": "Brandyn Burnette", "album_name": "sunset eyes"}, {"track_id": "3937JSF77MD6QJOfIJOKnK", "track_name": "Friends", "artist_name": "Elyse Jewel", "album_name": "Friends"}, {"track_id": "5NsdWdkHR3AScw6EKj51CA", "track_name": "Mourning", "artist_name": "Post Malone", "album_name": "AUSTIN (Bonus)"}, {"track_id": "1KMkcUvF7m3SDChDOa7i5L", "track_name": "WITHOUT YOU", "artist_name": "The Kid LAROI", "album_name": "F*CK LOVE 3+: OVER YOU"}, {"track_id": "0m7ZXpWWmcatvkMiEhZPo6", "track_name": "Pew Pew Pew", "artist_name": "Swxm", "album_name": "Pew Pew Pew"}, {"track_id": "58nTb0xUlvQdlPng9kKa8O", "track_name": "Trey P Fetty", "artist_name": "Trey P", "album_name": "Trey P Fetty"}, {"track_id": "18D7OqvuGj8gxE4oXVZGXT", "track_name": "Running Away", "artist_name": "Zzz.", "album_name": "Running Away"}, {"track_id": "6XO8RlYuJCiI0v3IA48FeJ", "track_name": "Bye Bye", "artist_name": "Marshmello", "album_name": "Bye Bye"}, {"track_id": "3GVkPk8mqxz0itaAriG1L7", "track_name": "Everybody Dies In Their Nightmares", "artist_name": "XXXTENTACION", "album_name": "17"}, {"track_id": "3vBTFVEcGhmH13Y0Lj9UTN", "track_name": "BULLET", "artist_name": "NF", "album_name": "HOPE"}, {"track_id": "5dOxHHMOFAbG3VH23t0xNm", "track_name": "Righteous", "artist_name": "Juice WRLD", "album_name": "Legends Never Die"}, {"track_id": "06JvOZ39sK8D8SqiqfaxDU", "track_name": "True Love", "artist_name": "Kanye West", "album_name": "True Love"}, {"track_id": "0FzEq5yepkq03NI8axcOBu", "track_name": "Save Me, Please", "artist_name": "Trippie Redd", "album_name": "First Draft"}, {"track_id": "202yaLntC4WM5V7odMhg9z", "track_name": "All I Never Wanted", "artist_name": "Zzz.", "album_name": "All I Never Wanted"}, {"track_id": "3ZEno9fORwMA1HPecdLi0R", "track_name": "HAPPY", "artist_name": "NF", "album_name": "HOPE"}, {"track_id": "4UKCKdYiLN6IMA5ZESUTL7", "track_name": "the remedy for a broken heart (why am I so in love)", "artist_name": "XXXTENTACION", "album_name": "?"}, {"track_id": "3fzryfEckroLBEkeAKiKYp", "track_name": "Tell Me", "artist_name": "YungMagnificent", "album_name": "716 Degrees"}, {"track_id": "285pBltuF7vW8TeWk8hdRR", "track_name": "Lucid Dreams", "artist_name": "Juice WRLD", "album_name": "Goodbye & Good Riddance"}, {"track_id": "4AxR3lHBMlOgQPVybCOslZ", "track_name": "So Long", "artist_name": "YungMagnificent", "album_name": "716 Degrees"}, {"track_id": "3ee8Jmje8o58CHK66QrVC2", "track_name": "SAD!", "artist_name": "XXXTENTACION", "album_name": "?"}, {"track_id": "5tCadSOz6WNCNr049GkZgK", "track_name": "Somebody", "artist_name": "Yung Pooda", "album_name": "Somebody"}, {"track_id": "5wWAwzGp2OaaoIkwcz6wZs", "track_name": "Life's A Mess (feat. Halsey)", "artist_name": "Juice WRLD", "album_name": "Legends Never Die"}, {"track_id": "7AQim7LbvFVZJE3O8TYgf2", "track_name": "Fuck Love", "artist_name": "XXXTENTACION", "album_name": "17"}, {"track_id": "7AFASza1mXqntmGtbxXprO", "track_name": "changes", "artist_name": "XXXTENTACION", "album_name": "?"}, {"track_id": "4y4spB9m0Q6026KfkAvy9Q", "track_name": "Lonely (with benny blanco)", "artist_name": "Justin Bieber", "album_name": "Lonely (with benny blanco)"}, {"track_id": "40DD3lGA9Xkp4InlWyqT9z", "track_name": "TELL ME WHY", "artist_name": "The Kid LAROI", "album_name": "F*CK LOVE 3+: OVER YOU"}, {"track_id": "4ZLzoOkj0MPWrTLvooIuaa", "track_name": "Get You The Moon (feat. Sn\u00f8w)", "artist_name": "Kina", "album_name": "Get You The Moon (feat. Sn\u00f8w)"}, {"track_id": "75ZvA4QfFiZvzhj2xkaWAh", "track_name": "I Fall Apart", "artist_name": "Post Malone", "album_name": "Stoney (Deluxe)"}, {"track_id": "01TnVDiet1DFTsyWKUKovl", "track_name": "NUMB", "artist_name": "XXXTENTACION", "album_name": "?"}, {"track_id": "5YnxnTS89l3FElIwfIAeSs", "track_name": "SO DONE", "artist_name": "The Kid LAROI", "album_name": "F*CK LOVE 3+: OVER YOU"}, {"track_id": "52okn5MNA47tk87PeZJLEL", "track_name": "Let You Down", "artist_name": "NF", "album_name": "Perception"}, {"track_id": "7dt6x5M1jzdTEt8oCbisTK", "track_name": "Better Now", "artist_name": "Post Malone", "album_name": "beerbongs & bentleys"}, {"track_id": "15og0pCEcTFWEXOFKdcJlU", "track_name": "Hate Me", "artist_name": "Ellie Goulding", "album_name": "Brightest Blue"}, {"track_id": "5ls62WNKHUUrdF3r1cv83T", "track_name": "emotions", "artist_name": "iann dior", "album_name": "nothings ever good enough"}, {"track_id": "7eJMfftS33KTjuF7lTsMCx", "track_name": "death bed (coffee for your head)", "artist_name": "Powfu", "album_name": "death bed (coffee for your head)"}, {"track_id": "4jvjzW7Hm0yK4LvvE0Paz9", "track_name": "Falling Down - Bonus Track", "artist_name": "Lil Peep", "album_name": "Come Over When You're Sober, Pt. 2"}, {"track_id": "7bSxVrKfyHDkjWjgObbl6z", "track_name": "Burn It Down", "artist_name": "Kjersti Long", "album_name": "Burn It Down"}, {"track_id": "5de9Ho64dovuQI8Uhn5gPD", "track_name": "I Don't Wanna Do This Anymore", "artist_name": "XXXTENTACION", "album_name": "Revenge"}, {"track_id": "3i6sCTU7ENlnHpHvrHUitW", "track_name": "Sometimes", "artist_name": "Juice WRLD", "album_name": "Fighting Demons (Deluxe)"}, {"track_id": "3NG9DUSmm78ay565a6QQdp", "track_name": "Somebody", "artist_name": "Yung Pooda", "album_name": "Somebody"}, {"track_id": "1r8ZCjfrQxoy2wVaBUbpwg", "track_name": "Thousand Miles", "artist_name": "The Kid LAROI", "album_name": "Thousand Miles"}, {"track_id": "6qiKCo71hFtk1lxPw6GpF0", "track_name": "you left", "artist_name": "mads", "album_name": "you left"}, {"track_id": "3GYlZ7tbxLOxe6ewMNVTkw", "track_name": "TV", "artist_name": "Billie Eilish", "album_name": "Guitar Songs"}, {"track_id": "7bdYxWPCs46dQ0XLwySOyv", "track_name": "better off", "artist_name": "Jeremy Zucker", "album_name": "glisten"}, {"track_id": "2gMXnyrvIjhVBUZwvLZDMP", "track_name": "Before You Go", "artist_name": "Lewis Capaldi", "album_name": "Divinely Uninspired To A Hellish Extent (Extended Edition)"}, {"track_id": "0nJW01T7XtvILxQgC5J7Wh", "track_name": "When I Was Your Man", "artist_name": "Bruno Mars", "album_name": "Unorthodox Jukebox"}, {"track_id": "2KnLkZ3z7PO3kgVGHGqDpD", "track_name": "It'll Be Okay", "artist_name": "Shawn Mendes", "album_name": "It'll Be Okay"}, {"track_id": "161DnLWsx1i3u1JT05lzqU", "track_name": "Talking to the Moon", "artist_name": "Bruno Mars", "album_name": "Doo-Wops & Hooligans"}, {"track_id": "75ls0gurX68lUmMjE7QcsE", "track_name": "all the kids are depressed", "artist_name": "Jeremy Zucker", "album_name": "glisten"}, {"track_id": "5CZ40GBx1sQ9agT82CLQCT", "track_name": "traitor", "artist_name": "Olivia Rodrigo", "album_name": "SOUR"}, {"track_id": "3FAJ6O0NOHQV8Mc5Ri6ENp", "track_name": "Heartbreak Anniversary", "artist_name": "Giveon", "album_name": "TAKE TIME"}, {"track_id": "4RX020eHQpZbZFP5jpbwOP", "track_name": "Coping", "artist_name": "Rosie Darling", "album_name": "Coping"}, {"track_id": "18uwL0vNUanqZH0ro2QcOP", "track_name": "comethru", "artist_name": "Jeremy Zucker", "album_name": "summer,"}, {"track_id": "5JCoSi02qi3jJeHdZXMmR8", "track_name": "favorite crime", "artist_name": "Olivia Rodrigo", "album_name": "SOUR"}, {"track_id": "4Of7rzpRpV1mWRbhp5rAqG", "track_name": "Bruises", "artist_name": "Lewis Capaldi", "album_name": "Divinely Uninspired To A Hellish Extent"}, {"track_id": "6y6jbcPG4Yn3Du4moXaenr", "track_name": "idfc", "artist_name": "blackbear", "album_name": "deadroses"}, {"track_id": "5dPz35akJjPqb17yeqNwqH", "track_name": "Ghost", "artist_name": "Justin Bieber", "album_name": "Justice"}, {"track_id": "1zejeOnykpCoyVSit6Bwp3", "track_name": "hope ur ok", "artist_name": "Olivia Rodrigo", "album_name": "SOUR"}, {"track_id": "3ZCTVFBt2Brf31RLEnCkWJ", "track_name": "everything i wanted", "artist_name": "Billie Eilish", "album_name": "everything i wanted"}, {"track_id": "0u2P5u6lvoDfwTYjAADbn4", "track_name": "lovely (with Khalid)", "artist_name": "Billie Eilish", "album_name": "lovely (with Khalid)"}, {"track_id": "3JvKfv6T31zO0ini8iNItO", "track_name": "Another Love", "artist_name": "Tom Odell", "album_name": "Long Way Down (Deluxe)"}, {"track_id": "0gplL1WMoJ6iYaPgMCL0gX", "track_name": "Easy On Me", "artist_name": "Adele", "album_name": "Easy On Me"}, {"track_id": "2JzZzZUQj3Qff7wapcbKjc", "track_name": "See You Again (feat. Charlie Puth)", "artist_name": "Wiz Khalifa", "album_name": "See You Again (feat. Charlie Puth)"}, {"track_id": "2eAvDnpXP5W0cVtiI0PUxV", "track_name": "Dandelions", "artist_name": "Ruth B.", "album_name": "Safe Haven"}, {"track_id": "3U4isOIWM3VvDubwSI3y7a", "track_name": "All of Me", "artist_name": "John Legend", "album_name": "Love In The Future (Expanded Edition)"}, {"track_id": "3zHq9ouUJQFQRf3cm1rRLu", "track_name": "Love Me Like You Do - From \"Fifty Shades Of Grey\"", "artist_name": "Ellie Goulding", "album_name": "Delirium (Deluxe)"}, {"track_id": "04sN26COy28wTXYj3dMoiZ", "track_name": "Bored", "artist_name": "Billie Eilish", "album_name": "Bored"}, {"track_id": "1HNkqx9Ahdgi1Ixy2xkKkL", "track_name": "Photograph", "artist_name": "Ed Sheeran", "album_name": "x (Deluxe Edition)"}, {"track_id": "5tz69p7tJuGPeMGwNTxYuV", "track_name": "1-800-273-8255", "artist_name": "Logic", "album_name": "Everybody"}, {"track_id": "3bNv3VuUOKgrf5hu3YcuRo", "track_name": "Someone Like You", "artist_name": "Adele", "album_name": "21"}, {"track_id": "1ZMiCix7XSAbfAJlEZWMCp", "track_name": "Falling", "artist_name": "Harry Styles", "album_name": "Fine Line"}, {"track_id": "6FZDfxM3a3UCqtzo5pxSLZ", "track_name": "Without Me", "artist_name": "Halsey", "album_name": "Manic"}, {"track_id": "0BCPKOYdS2jbQ8iyB56Zns", "track_name": "Clocks", "artist_name": "Coldplay", "album_name": "A Rush of Blood to the Head"}, {"track_id": "43zdsphuZLzwA9k4DJhU0I", "track_name": "when the party's over", "artist_name": "Billie Eilish", "album_name": "WHEN WE ALL FALL ASLEEP, WHERE DO WE GO?"}, {"track_id": "09mEdoA6zrmBPgTEN5qXmN", "track_name": "Call Out My Name", "artist_name": "The Weeknd", "album_name": "My Dear Melancholy,"}, {"track_id": "50kpGaPAhYJ3sGmk6vplg0", "track_name": "Love Yourself", "artist_name": "Justin Bieber", "album_name": "Purpose (Deluxe)"}, {"track_id": "5Nm9ERjJZ5oyfXZTECKmRt", "track_name": "Stay With Me", "artist_name": "Sam Smith", "album_name": "In The Lonely Hour"}, {"track_id": "1mXVgsBdtIVeCLJnSnmtdV", "track_name": "Too Good At Goodbyes", "artist_name": "Sam Smith", "album_name": "The Thrill Of It All (Special Edition)"}, {"track_id": "2qxmye6gAegTMjLKEBoR3d", "track_name": "Let Me Down Slowly", "artist_name": "Alec Benjamin", "album_name": "Narrated For You"}, {"track_id": "5uCax9HTNlzGybIStD3vDh", "track_name": "Say You Won't Let Go", "artist_name": "James Arthur", "album_name": "Back from the Edge"}, {"track_id": "2NbsBSshscKIPRG3kwBbfo", "track_name": "Never Felt So Alone", "artist_name": "Labrinth", "album_name": "Never Felt So Alone"}]